src/__init__.py
svtter_template_creator/__init__.py
svtter_template_creator/__main__.py
svtter_template_creator/lib.py
svtter_template_creator/repl.py
svtter_template_creator/tests/__init__.py
svtter_template_creator/utils.py
svtter_template_creator-0.7.0.dist-info/entry_points.txt
svtter_template_creator-0.7.0.dist-info/LICENSE
svtter_template_creator-0.7.0.dist-info/METADATA
svtter_template_creator-0.7.0.dist-info/WHEEL
svtter_template_creator-0.7.0.dist-info/RECORD
